Metadata-Version: 2.4
Name: getconsult
Version: 0.7.1
Summary: Multi-agent consensus system - LLM agents with different prompts analyze problems, critique each other, iterate to agreement
Author-email: Pruthvi Kumar <pruthvikumar.123@gmail.com>
Maintainer-email: Pruthvi Kumar <pruthvikumar.123@gmail.com>
License-Expression: LicenseRef-Proprietary
Project-URL: Homepage, https://github.com/1x-eng/agentic-atlas
Project-URL: Bug Tracker, https://github.com/1x-eng/consult-issues/issues
Project-URL: Documentation, https://github.com/1x-eng/agentic-atlas#readme
Keywords: ai,agents,autogen,llm,consensus,multi-agent
Classifier: Development Status :: 4 - Beta
Classifier: Intended Audience :: Developers
Classifier: Programming Language :: Python :: 3
Classifier: Programming Language :: Python :: 3.10
Classifier: Programming Language :: Python :: 3.11
Classifier: Programming Language :: Python :: 3.12
Classifier: Topic :: Software Development :: Libraries :: Python Modules
Classifier: Topic :: Scientific/Engineering :: Artificial Intelligence
Requires-Python: >=3.10
License-File: LICENSE
Requires-Dist: autogen-agentchat>=0.4.0
Requires-Dist: autogen-ext[anthropic,openai]>=0.4.0
Requires-Dist: python-dotenv>=1.0.0
Requires-Dist: pydantic>=2.0.0
Requires-Dist: rich>=13.0.0
Requires-Dist: textual>=0.40.0
Requires-Dist: Pillow>=10.0.0
Requires-Dist: PyMuPDF>=1.23.0
Provides-Extra: dev
Requires-Dist: pytest>=7.0.0; extra == "dev"
Requires-Dist: pytest-asyncio>=0.21.0; extra == "dev"
Requires-Dist: black>=23.0.0; extra == "dev"
Requires-Dist: isort>=5.12.0; extra == "dev"
Requires-Dist: flake8>=6.0.0; extra == "dev"
Requires-Dist: mypy>=1.0.0; extra == "dev"
Dynamic: license-file
